yoloweb/__init__.py
yoloweb/app.py
yoloweb/config.py
yoloweb/detector.py
yoloweb/main.py
yoloweb/templates/index.html
yoloweb-1.0.0.dist-info/METADATA
yoloweb-1.0.0.dist-info/WHEEL
yoloweb-1.0.0.dist-info/entry_points.txt
yoloweb-1.0.0.dist-info/top_level.txt
yoloweb-1.0.0.dist-info/RECORD
