Metadata-Version: 2.1
Name: yoloweb
Version: 1.0.0
Summary: 通用YOLO检测Web服务，支持动态模型替换
Author-email: YOLOWeb Team <your-email@example.com>
Project-URL: Homepage, https://github.com/yourusername/yoloweb
Project-URL: Repository, https://github.com/yourusername/yoloweb
Project-URL: Bug Reports, https://github.com/yourusername/yoloweb/issues
Keywords: yolo,detection,web,opencv,computer-vision
Classifier: Development Status :: 4 - Beta
Classifier: Intended Audience :: Developers
Classifier: Operating System :: OS Independent
Classifier: Programming Language :: Python :: 3
Classifier: Programming Language :: Python :: 3.8
Classifier: Programming Language :: Python :: 3.9
Classifier: Programming Language :: Python :: 3.10
Classifier: Programming Language :: Python :: 3.11
Classifier: Topic :: Scientific/Engineering :: Artificial Intelligence
Classifier: Topic :: Software Development :: Libraries :: Python Modules
Requires-Python: >=3.8
Requires-Dist: Flask>=2.3.0
Requires-Dist: ultralytics>=8.0.0
Requires-Dist: opencv-python>=4.8.0
Requires-Dist: numpy>=1.24.0
Requires-Dist: Pillow>=10.0.0
Requires-Dist: supervision>=0.16.0
Requires-Dist: torch>=2.0.0
Requires-Dist: torchvision>=0.15.0
Requires-Dist: requests>=2.31.0
Requires-Dist: gunicorn>=21.2.0
